SARW/__init__.py
SARW/calculator.py
SARW/glove.py
SARW/parser.py
SARW-0.1.1.dist-info/LICENSE
SARW-0.1.1.dist-info/METADATA
SARW-0.1.1.dist-info/WHEEL
SARW-0.1.1.dist-info/top_level.txt
SARW-0.1.1.dist-info/zip-safe
SARW-0.1.1.dist-info/RECORD
